fortune_teller/__init__.py
fortune_teller/cs_fortune.py
fortune_teller/date_time.py
fortune_teller/fortune_stories.py
fortune_teller/get_started.py
fortune_teller/mood_fortune.py
fortune_teller2607555-0.1.1.dist-info/licenses/LICENSE
fortune_teller2607555-0.1.1.dist-info/METADATA
fortune_teller2607555-0.1.1.dist-info/WHEEL
fortune_teller2607555-0.1.1.dist-info/top_level.txt
fortune_teller2607555-0.1.1.dist-info/RECORD
