Metadata-Version: 2.4
Name: fortune-teller2607555
Version: 0.1.1
Summary: A fun Python package that generates random fortunes with a date.
Author: Brian, Naz, Jibril, Polina
License: MIT
Requires-Python: >=3.9
License-File: LICENSE
Provides-Extra: dev
Requires-Dist: pytest; extra == "dev"
Dynamic: license-file
